odoo/addons/maintenance_inspection/README.rst
odoo/addons/maintenance_inspection/__init__.py
odoo/addons/maintenance_inspection/__manifest__.py
odoo/addons/maintenance_inspection/i18n/fr.po
odoo/addons/maintenance_inspection/i18n/it.po
odoo/addons/maintenance_inspection/i18n/maintenance_inspection.pot
odoo/addons/maintenance_inspection/models/__init__.py
odoo/addons/maintenance_inspection/models/maintenance_equipment.py
odoo/addons/maintenance_inspection/models/maintenance_inspection_item.py
odoo/addons/maintenance_inspection/models/maintenance_inspection_line.py
odoo/addons/maintenance_inspection/models/maintenance_plan.py
odoo/addons/maintenance_inspection/models/maintenance_request.py
odoo/addons/maintenance_inspection/readme/CONTRIBUTORS.rst
odoo/addons/maintenance_inspection/readme/DESCRIPTION.rst
odoo/addons/maintenance_inspection/readme/USAGE.rst
odoo/addons/maintenance_inspection/security/ir.model.access.csv
odoo/addons/maintenance_inspection/static/description/icon.png
odoo/addons/maintenance_inspection/static/description/index.html
odoo/addons/maintenance_inspection/tests/__init__.py
odoo/addons/maintenance_inspection/tests/test_inspection.py
odoo/addons/maintenance_inspection/views/maintenance_inspection_item.xml
odoo/addons/maintenance_inspection/views/maintenance_inspection_line.xml
odoo/addons/maintenance_inspection/views/maintenance_plan.xml
odoo/addons/maintenance_inspection/views/maintenance_request.xml
odoo14_addon_maintenance_inspection-14.0.1.0.1.dev4.dist-info/METADATA
odoo14_addon_maintenance_inspection-14.0.1.0.1.dev4.dist-info/WHEEL
odoo14_addon_maintenance_inspection-14.0.1.0.1.dev4.dist-info/top_level.txt
odoo14_addon_maintenance_inspection-14.0.1.0.1.dev4.dist-info/RECORD
