Metadata-Version: 2.1
Name: odoo14-addon-maintenance_inspection
Version: 14.0.1.0.1.dev4
Summary: Allow to manage inspections inside Preventive requests
Home-page: https://github.com/OCA/maintenance
Author: Dixmit,Odoo Community Association (OCA)
Author-email: support@odoo-community.org
License: AGPL-3
Classifier: Programming Language :: Python
Classifier: Framework :: Odoo
Classifier: Framework :: Odoo :: 14.0
Classifier: License :: OSI Approved :: GNU Affero General Public License v3
Requires-Python: >=3.6
Requires-Dist: odoo14-addon-base-maintenance
Requires-Dist: odoo14-addon-maintenance-plan
Requires-Dist: odoo<14.1dev,>=14.0a
